{
    "version":  "1.0.9",
    "buildTimestamp":  "2025-04-19T08:57:57.8750000",
    "systemData":  [
                       {
                           "id":  "20250511140439-d890b60a",
                           "date":  "2025-04-26",
                           "type":  "system_update"
                       },
                       {
                           "id":  "20250511140439-edf94cf2",
                           "date":  "2025-04-16",
                           "type":  "system_update"
                       },
                       {
                           "id":  "20250511140440-525718c7",
                           "date":  "2025-05-10",
                           "type":  "system_update"
                       },
                       {
                           "id":  "20250511140441-3f4fe14d",
                           "date":  "2025-04-25",
                           "type":  "system_update"
                       },
                       {
                           "id":  "20250511140441-a83e89f2",
                           "date":  "2025-05-07",
                           "type":  "system_update"
                       },
                       {
                           "id":  "20250511140442-aa4cc37d",
                           "date":  "2025-04-19",
                           "type":  "system_update"
                       }
                   ],
    "appConfig":  {
                      "features":  {
                                       "analytics":  true,
                                       "notifications":  false,
                                       "recommendations":  true,
                                       "tutoring":  true
                                   }
                  }
}
